windows_pathlib/__init__.py
windows_pathlib/main.py
windows_pathlib-0.0.1.dist-info/METADATA
windows_pathlib-0.0.1.dist-info/WHEEL
windows_pathlib-0.0.1.dist-info/top_level.txt
windows_pathlib-0.0.1.dist-info/RECORD
