Metadata-Version: 2.1
Name: windows_pathlib
Version: 0.0.1
Summary: Best Practices for Handling Paths in Windows.
Home-page: https://github.com/fa0311/windows_pathlib
Author: yuki
Author-email: yuki@yuki0311.com
License: MIT
Keywords: pathlib
